hypothesis_pandas/__init__.py
hypothesis_pandas/hypothesis_pandas.py
hypothesis_pandas-0.2.7.dist-info/METADATA
hypothesis_pandas-0.2.7.dist-info/WHEEL
hypothesis_pandas-0.2.7.dist-info/top_level.txt
hypothesis_pandas-0.2.7.dist-info/RECORD
